LICENSE
MANIFEST.in
README.md
README.rst
setup.py
kshingle/__init__.py
kshingle/cews.py
kshingle/cews_cpu.py
kshingle/metrics.py
kshingle/shingleseqs.py
kshingle/shingleset.py
kshingle/vocab.py
kshingle/wildcard.py
kshingle.egg-info/PKG-INFO
kshingle.egg-info/SOURCES.txt
kshingle.egg-info/dependency_links.txt
kshingle.egg-info/requires.txt
kshingle.egg-info/top_level.txt
kshingle.egg-info/zip-safe
test/__init__.py
test/test_cews.py
test/test_cews_cpu.py
test/test_identify_vocab.py
test/test_metrics.py
test/test_shingleseqs.py
test/test_shingleset.py