Metadata-Version: 2.1
Name: kshingle
Version: 0.9.5
Summary: Split strings into (character-based) k-shingles
Home-page: http://github.com/ulf1/kshingle
Author: Ulf Hamster
Author-email: 554c46@gmail.com
License: Apache License 2.0
Platform: UNKNOWN
Requires-Python: >=3.6
License-File: LICENSE
